cluster_crit/__init__.py
cluster_crit/cluster.py
cluster_crit/criteria.py
cluster_crit-1.0.1.dist-info/METADATA
cluster_crit-1.0.1.dist-info/WHEEL
cluster_crit-1.0.1.dist-info/top_level.txt
cluster_crit-1.0.1.dist-info/RECORD
