Metadata-Version: 2.1
Name: cluster-crit
Version: 1.0.1
Summary: Calculate various internal clustering validation or quality criteria.
Home-page: https://github.com/barbacbd/ClusterCrit
Author: Brent Barbachem
Author-email: barbacbd@dukes.jmu.edu
Maintainer: Brent Barbachem
Maintainer-email: barbacbd@dukes.jmu.edu
License: MIT
Keywords: cluster,crit,criteria,selection
Classifier: Intended Audience :: Developers
Classifier: Intended Audience :: Education
Classifier: Intended Audience :: Other Audience
Classifier: Intended Audience :: Science/Research
Classifier: Natural Language :: English
Classifier: Operating System :: POSIX :: Linux
Classifier: Programming Language :: Python :: 3
Classifier: Programming Language :: Python :: 3.7
Classifier: Programming Language :: Python :: 3.8
Classifier: Programming Language :: Python :: 3.9
Classifier: Programming Language :: Python :: 3.10
Classifier: Topic :: Software Development
Requires-Python: <4,>=3.7
Requires-Dist: pandas
Requires-Dist: numpy
Requires-Dist: rpy2
